wasmfunc/__init__.py
wasmfunc/__main__.py
wasmfunc/compiler.py
wasmfunc/decorators.py
wasmfunc/file_handler.py
wasmfunc/mini_std.py
wasmfunc/pre_compiler.py
wasmfunc/runWasmGC.js
wasmfunc/types.py
wasmfunc-0.0.1.dist-info/LICENSE
wasmfunc-0.0.1.dist-info/METADATA
wasmfunc-0.0.1.dist-info/WHEEL
wasmfunc-0.0.1.dist-info/entry_points.txt
wasmfunc-0.0.1.dist-info/top_level.txt
wasmfunc-0.0.1.dist-info/RECORD
