Metadata-Version: 2.1
Name: wasmfunc
Version: 0.0.1
Summary: A WebAssembly compiler for Python
Author-email: Jonathan Hargreaves <jhargreaves189@gmail.com>
License: Apache License
Project-URL: Source Code, https://github.com/jonathanharg/wasmfunc
Project-URL: Issues, https://github.com/jonathanharg/wasmfunc/issues
Keywords: WebAssembly,Compiler
Classifier: Environment :: MacOS X
Classifier: Environment :: WebAssembly
Classifier: Environment :: Win32 (MS Windows)
Classifier: Intended Audience :: Developers
Classifier: License :: OSI Approved :: Apache Software License
Classifier: Natural Language :: English
Classifier: Operating System :: MacOS
Classifier: Operating System :: Microsoft :: Windows
Classifier: Operating System :: POSIX :: Linux
Classifier: Programming Language :: Python
Classifier: Topic :: Software Development :: Compilers
Requires-Python: >=3.12
License-File: LICENSE
Requires-Dist: binaryen.py >=117.1.0
Requires-Dist: wasmtime
Provides-Extra: dev
Requires-Dist: black ; extra == 'dev'
Requires-Dist: isort ; extra == 'dev'
Requires-Dist: pytest ; extra == 'dev'
Requires-Dist: build ; extra == 'dev'
